raider_admin/__init__.py
raider_admin/raider.py
tests/__init__.py
tests/test_admin.py
py_raider_admin-1.0.1.dist-info/LICENSE
py_raider_admin-1.0.1.dist-info/METADATA
py_raider_admin-1.0.1.dist-info/WHEEL
py_raider_admin-1.0.1.dist-info/top_level.txt
py_raider_admin-1.0.1.dist-info/RECORD
