Metadata-Version: 2.1
Name: py-raider-admin
Version: 1.0.1
Summary: Raider admin interface for Python
Home-page: https://github.com/M0r13n/py-raider-admin
Author: Leon Morten Richter
Author-email: leon.morten@gmail.com
License: MIT
Platform: UNKNOWN
Classifier: License :: OSI Approved :: MIT License
Classifier: Programming Language :: Python :: 3
Classifier: Programming Language :: Python :: 3.7
Requires-Python: >=3.6
Requires-Dist: mysql-connector-python
